odoo10_addon_l10n_es-10.0.1.3.0-py2.7-nspkg.pth
odoo/addons/l10n_es/README.rst
odoo/addons/l10n_es/__init__.py
odoo/addons/l10n_es/__manifest__.py
odoo/addons/l10n_es/data/account_account_assoc.xml
odoo/addons/l10n_es/data/account_account_common.xml
odoo/addons/l10n_es/data/account_account_full.xml
odoo/addons/l10n_es/data/account_account_pymes.xml
odoo/addons/l10n_es/data/account_chart_template.xml
odoo/addons/l10n_es/data/account_chart_template_post.xml
odoo/addons/l10n_es/data/account_type.xml
odoo/addons/l10n_es/data/fiscal_positions_common.xml
odoo/addons/l10n_es/data/tax_codes_common.xml
odoo/addons/l10n_es/data/taxes_common.xml
odoo/addons/l10n_es/i18n/ar.po
odoo/addons/l10n_es/i18n/ca.po
odoo/addons/l10n_es/i18n/da.po
odoo/addons/l10n_es/i18n/de.po
odoo/addons/l10n_es/i18n/es.po
odoo/addons/l10n_es/i18n/es_CR.po
odoo/addons/l10n_es/i18n/es_ES.po
odoo/addons/l10n_es/i18n/es_MX.po
odoo/addons/l10n_es/i18n/es_PY.po
odoo/addons/l10n_es/i18n/es_VE.po
odoo/addons/l10n_es/i18n/fr.po
odoo/addons/l10n_es/i18n/gl.po
odoo/addons/l10n_es/i18n/hu.po
odoo/addons/l10n_es/i18n/it.po
odoo/addons/l10n_es/i18n/nl.po
odoo/addons/l10n_es/i18n/oc.po
odoo/addons/l10n_es/i18n/pt.po
odoo/addons/l10n_es/i18n/pt_BR.po
odoo/addons/l10n_es/i18n/sl.po
odoo/addons/l10n_es/i18n/sr@latin.po
odoo/addons/l10n_es/i18n/tr.po
odoo/addons/l10n_es/images/config_chart_l10n_es.png
odoo/addons/l10n_es/images/l10n_es_chart.png
odoo/addons/l10n_es/static/description/icon.png
odoo/addons/l10n_es/tests/__init__.py
odoo/addons/l10n_es/tests/test_l10n_es.py
odoo10_addon_l10n_es-10.0.1.3.0.dist-info/DESCRIPTION.rst
odoo10_addon_l10n_es-10.0.1.3.0.dist-info/METADATA
odoo10_addon_l10n_es-10.0.1.3.0.dist-info/RECORD
odoo10_addon_l10n_es-10.0.1.3.0.dist-info/WHEEL
odoo10_addon_l10n_es-10.0.1.3.0.dist-info/metadata.json
odoo10_addon_l10n_es-10.0.1.3.0.dist-info/namespace_packages.txt
odoo10_addon_l10n_es-10.0.1.3.0.dist-info/top_level.txt
