Metadata-Version: 2.0
Name: odoo10-addon-l10n-es
Version: 10.0.1.3.0
Summary: Planes de cuentas españoles (según PGCE 2008)
Home-page: https://github.com/OCA/l10n-spain
Author: Spanish Localization Team, Odoo Community Association (OCA)
Author-email: support@odoo-community.org
License: AGPL-3
Platform: UNKNOWN
Classifier: Programming Language :: Python
Classifier: Framework :: Odoo
Classifier: License :: OSI Approved :: GNU Affero General Public License v3
Requires-Python: ~=2.7
Requires-Dist: odoo (<10.1dev,>=10.0)
